{"data":[{"DistrictID":1902,"ProvinceID":208,"DistrictName":"Huyện Cam Lâm"},{"DistrictID":1739,"ProvinceID":208,"DistrictName":"Huyện Diên Khánh"},{"DistrictID":3212,"ProvinceID":208,"DistrictName":"Huyện Khánh Sơn"},{"DistrictID":3213,"ProvinceID":208,"DistrictName":"Huyện Khánh Vĩnh"},{"DistrictID":1829,"ProvinceID":208,"DistrictName":"Huyện Vạn Ninh"},{"DistrictID":2117,"ProvinceID":208,"DistrictName":"Huyện đảo Trường Sa"},{"DistrictID":1664,"ProvinceID":208,"DistrictName":"Thành phố Cam Ranh"},{"DistrictID":1548,"ProvinceID":208,"DistrictName":"Thành phố Nha Trang"},{"DistrictID":2061,"ProvinceID":208,"DistrictName":"Thị xã Ninh Hòa"}]}