{"data":[{"WardCode":"20201","DistrictID":1443,"WardName":"Phường An Khánh"},{"WardCode":"20202","DistrictID":1443,"WardName":"Phường An Lợi Đông"},{"WardCode":"20203","DistrictID":1443,"WardName":"Phường An Phú"},{"WardCode":"20204","DistrictID":1443,"WardName":"Phường Bình An"},{"WardCode":"20205","DistrictID":1443,"WardName":"Phường Bình Khánh"},{"WardCode":"20207","DistrictID":1443,"WardName":"Phường Bình Trưng Tây"},{"WardCode":"20206","DistrictID":1443,"WardName":"Phường Bình Trưng Đông"},{"WardCode":"20208","DistrictID":1443,"WardName":"Phường Cát Lái"},{"WardCode":"20209","DistrictID":1443,"WardName":"Phường Thạnh Mỹ Lợi"},{"WardCode":"20210","DistrictID":1443,"WardName":"Phường Thảo Điền"},{"WardCode":"20211","DistrictID":1443,"WardName":"Phường Thủ Thiêm"}]}