{"data":[{"WardCode":"1A0401","DistrictID":1486,"WardName":"Phường Cát Linh"},{"WardCode":"1A0402","DistrictID":1486,"WardName":"Phường Hàng Bột"},{"WardCode":"1A0403","DistrictID":1486,"WardName":"Phường Khâm Thiên"},{"WardCode":"1A0404","DistrictID":1486,"WardName":"Phường Khương Thượng"},{"WardCode":"1A0405","DistrictID":1486,"WardName":"Phường Kim Liên"},{"WardCode":"1A0406","DistrictID":1486,"WardName":"Phường Láng Hạ"},{"WardCode":"1A0407","DistrictID":1486,"WardName":"Phường Láng Thượng"},{"WardCode":"1A0408","DistrictID":1486,"WardName":"Phường Nam Đồng"},{"WardCode":"1A0409","DistrictID":1486,"WardName":"Phường Ngã Tư Sở"},{"WardCode":"1A0411","DistrictID":1486,"WardName":"Phường Phương Liên"},{"WardCode":"91259","DistrictID":1486,"WardName":"Phường Phương Liên - Trung Tự"},{"WardCode":"1A0412","DistrictID":1486,"WardName":"Phường Phương Mai"},{"WardCode":"1A0413","DistrictID":1486,"WardName":"Phường Quang Trung"},{"WardCode":"1A0414","DistrictID":1486,"WardName":"Phường Quốc Tử Giám"},{"WardCode":"1A0415","DistrictID":1486,"WardName":"Phường Thịnh Quang"},{"WardCode":"1A0416","DistrictID":1486,"WardName":"Phường Thổ Quan"},{"WardCode":"1A0417","DistrictID":1486,"WardName":"Phường Trung Liệt"},{"WardCode":"1A0418","DistrictID":1486,"WardName":"Phường Trung Phụng"},{"WardCode":"1A0419","DistrictID":1486,"WardName":"Phường Trung Tự"},{"WardCode":"1A0420","DistrictID":1486,"WardName":"Phường Văn Chương"},{"WardCode":"1A0421","DistrictID":1486,"WardName":"Phường Văn Miếu"},{"WardCode":"91258","DistrictID":1486,"WardName":"Phường Văn Miếu - Quốc Tử Giám"},{"WardCode":"1A0410","DistrictID":1486,"WardName":"Phường Ô Chợ Dừa"}]}