{"data":[{"WardCode":"460110","DistrictID":1626,"WardName":"Xã Thạnh Tân"},{"WardCode":"460109","DistrictID":1626,"WardName":"Xã Tân Bình"},{"WardCode":"460108","DistrictID":1626,"WardName":"Xã Bình Minh"},{"WardCode":"460107","DistrictID":1626,"WardName":"Phường Ninh Thạnh"},{"WardCode":"460106","DistrictID":1626,"WardName":"Phường Ninh Sơn"},{"WardCode":"460105","DistrictID":1626,"WardName":"Phường Hiệp Ninh"},{"WardCode":"460104","DistrictID":1626,"WardName":"Phường 4"},{"WardCode":"460103","DistrictID":1626,"WardName":"Phường 3"},{"WardCode":"460102","DistrictID":1626,"WardName":"Phường 2"},{"WardCode":"460101","DistrictID":1626,"WardName":"Phường 1"}]}