{"data":[{"WardCode":"510813","DistrictID":1758,"WardName":"Xã Vĩnh Thạnh Trung"},{"WardCode":"510812","DistrictID":1758,"WardName":"Xã Thạnh Mỹ Tây"},{"WardCode":"510811","DistrictID":1758,"WardName":"Xã Ô Long Vỹ"},{"WardCode":"510810","DistrictID":1758,"WardName":"Xã Mỹ Phú"},{"WardCode":"510809","DistrictID":1758,"WardName":"Xã Mỹ Đức"},{"WardCode":"510808","DistrictID":1758,"WardName":"Xã Khánh Hòa"},{"WardCode":"510807","DistrictID":1758,"WardName":"Xã Đào Hữu Cảnh"},{"WardCode":"510806","DistrictID":1758,"WardName":"Xã Bình Thủy"},{"WardCode":"510805","DistrictID":1758,"WardName":"Xã Bình Phú"},{"WardCode":"510804","DistrictID":1758,"WardName":"Xã Bình Mỹ"},{"WardCode":"510803","DistrictID":1758,"WardName":"Xã Bình Long"},{"WardCode":"510802","DistrictID":1758,"WardName":"Xã Bình Chánh"},{"WardCode":"510801","DistrictID":1758,"WardName":"Thị trấn Cái Dầu"}]}