{"data":[{"WardCode":"180221","DistrictID":1765,"WardName":"Xã Xuân Lương"},{"WardCode":"180220","DistrictID":1765,"WardName":"Xã Tiến Thắng"},{"WardCode":"180219","DistrictID":1765,"WardName":"Xã Tân Sỏi"},{"WardCode":"180218","DistrictID":1765,"WardName":"Xã Tân Hiệp"},{"WardCode":"180217","DistrictID":1765,"WardName":"Xã Tam Tiến"},{"WardCode":"180216","DistrictID":1765,"WardName":"Xã Tam Hiệp"},{"WardCode":"180215","DistrictID":1765,"WardName":"Thị trấn Phồn Xương"},{"WardCode":"180214","DistrictID":1765,"WardName":"Xã Hương Vĩ"},{"WardCode":"180213","DistrictID":1765,"WardName":"Xã Hồng Kỳ"},{"WardCode":"180212","DistrictID":1765,"WardName":"Xã Đồng Vương"},{"WardCode":"180211","DistrictID":1765,"WardName":"Xã Đồng Tiến"},{"WardCode":"180210","DistrictID":1765,"WardName":"Xã Đồng Tâm"},{"WardCode":"180209","DistrictID":1765,"WardName":"Xã Đông Sơn"},{"WardCode":"180208","DistrictID":1765,"WardName":"Xã Đồng Lạc"},{"WardCode":"180207","DistrictID":1765,"WardName":"Xã Đồng Kỳ"},{"WardCode":"180206","DistrictID":1765,"WardName":"Xã Đồng Hưu"},{"WardCode":"180205","DistrictID":1765,"WardName":"Xã Canh Nậu"},{"WardCode":"180204","DistrictID":1765,"WardName":"Xã Bố Hạ"},{"WardCode":"180203","DistrictID":1765,"WardName":"Xã An Thượng"},{"WardCode":"180202","DistrictID":1765,"WardName":"Thị trấn Cầu Gồ"},{"WardCode":"180201","DistrictID":1765,"WardName":"Thị trấn Bố Hạ"}]}