{"data":[{"WardCode":"471009","DistrictID":1778,"WardName":"Xã Tân Tiến"},{"WardCode":"471008","DistrictID":1778,"WardName":"Xã Tân Phước"},{"WardCode":"471007","DistrictID":1778,"WardName":"Xã Tân Hải"},{"WardCode":"471006","DistrictID":1778,"WardName":"Xã Tân Bình"},{"WardCode":"471005","DistrictID":1778,"WardName":"Phường Tân Thiện"},{"WardCode":"471004","DistrictID":1778,"WardName":"Phường Tân An"},{"WardCode":"471003","DistrictID":1778,"WardName":"Phường Phước Lộc"},{"WardCode":"471002","DistrictID":1778,"WardName":"Phường Phước Hội"},{"WardCode":"471001","DistrictID":1778,"WardName":"Phường Bình Tân"}]}