{"data":[{"WardCode":"42111","DistrictID":1839,"WardName":"Thị trấn Lộc Thắng"},{"WardCode":"761202","DistrictID":1839,"WardName":"Xã B' Lá"},{"WardCode":"761203","DistrictID":1839,"WardName":"Xã Lộc An"},{"WardCode":"761205","DistrictID":1839,"WardName":"Xã Lộc Bảo"},{"WardCode":"761204","DistrictID":1839,"WardName":"Xã Lộc Bắc"},{"WardCode":"761207","DistrictID":1839,"WardName":"Xã Lộc Lâm"},{"WardCode":"761208","DistrictID":1839,"WardName":"Xã Lộc Nam"},{"WardCode":"761209","DistrictID":1839,"WardName":"Xã Lộc Ngãi"},{"WardCode":"761210","DistrictID":1839,"WardName":"Xã Lộc Phú"},{"WardCode":"761211","DistrictID":1839,"WardName":"Xã Lộc Quảng"},{"WardCode":"761213","DistrictID":1839,"WardName":"Xã Lộc Thành"},{"WardCode":"761212","DistrictID":1839,"WardName":"Xã Lộc Tân"},{"WardCode":"761206","DistrictID":1839,"WardName":"Xã Lộc Đức"},{"WardCode":"90772","DistrictID":1839,"WardName":"Xã Nam Quang"},{"WardCode":"761214","DistrictID":1839,"WardName":"Xã Tân Lạc"}]}