{"data":[{"WardCode":"320501","DistrictID":1903,"WardName":"Thị trấn Cam Lộ"},{"WardCode":"320502","DistrictID":1903,"WardName":"Xã Cam An"},{"WardCode":"320503","DistrictID":1903,"WardName":"Xã Cam Chính"},{"WardCode":"320504","DistrictID":1903,"WardName":"Xã Cam Hiếu"},{"WardCode":"320505","DistrictID":1903,"WardName":"Xã Cam Nghĩa"},{"WardCode":"320506","DistrictID":1903,"WardName":"Xã Cam Thanh"},{"WardCode":"320507","DistrictID":1903,"WardName":"Xã Cam Thành"},{"WardCode":"320508","DistrictID":1903,"WardName":"Xã Cam Thủy"},{"WardCode":"320509","DistrictID":1903,"WardName":"Xã Cam Tuyền"},{"WardCode":"800110","DistrictID":1903,"WardName":"Xã Thanh An"}]}