{"data":[{"WardCode":"100801","DistrictID":1963,"WardName":"Thị trấn Lộc Bình"},{"WardCode":"100802","DistrictID":1963,"WardName":"Thị trấn Na Dương"},{"WardCode":"100806","DistrictID":1963,"WardName":"Thị trấn Đông Quan"},{"WardCode":"100804","DistrictID":1963,"WardName":"Xã Bằng Khánh"},{"WardCode":"100807","DistrictID":1963,"WardName":"Xã Hiệp Hạ"},{"WardCode":"100808","DistrictID":1963,"WardName":"Xã Hữu Khánh"},{"WardCode":"100809","DistrictID":1963,"WardName":"Xã Hữu Lân"},{"WardCode":"100810","DistrictID":1963,"WardName":"Xã Khuất Xá"},{"WardCode":"800075","DistrictID":1963,"WardName":"Xã Khánh Xuân"},{"WardCode":"100811","DistrictID":1963,"WardName":"Xã Lợi Bác"},{"WardCode":"100812","DistrictID":1963,"WardName":"Xã Lục Thôn"},{"WardCode":"800076","DistrictID":1963,"WardName":"Xã Minh Hiệp"},{"WardCode":"100814","DistrictID":1963,"WardName":"Xã Minh Phát"},{"WardCode":"100813","DistrictID":1963,"WardName":"Xã Mẫu Sơn"},{"WardCode":"100815","DistrictID":1963,"WardName":"Xã Nam Quan"},{"WardCode":"100816","DistrictID":1963,"WardName":"Xã Như Khuê"},{"WardCode":"100817","DistrictID":1963,"WardName":"Xã Nhượng Bạn"},{"WardCode":"100818","DistrictID":1963,"WardName":"Xã Quan Bản"},{"WardCode":"100819","DistrictID":1963,"WardName":"Xã Sàn Viên"},{"WardCode":"100820","DistrictID":1963,"WardName":"Xã Tam Gia"},{"WardCode":"800077","DistrictID":1963,"WardName":"Xã Thống Nhất"},{"WardCode":"100823","DistrictID":1963,"WardName":"Xã Tú Mịch"},{"WardCode":"100822","DistrictID":1963,"WardName":"Xã Tú Đoạn"},{"WardCode":"100821","DistrictID":1963,"WardName":"Xã Tĩnh Bắc"},{"WardCode":"100824","DistrictID":1963,"WardName":"Xã Vân Mộng"},{"WardCode":"100825","DistrictID":1963,"WardName":"Xã Xuân Dương"},{"WardCode":"100826","DistrictID":1963,"WardName":"Xã Xuân Lễ"},{"WardCode":"100827","DistrictID":1963,"WardName":"Xã Xuân Mãn"},{"WardCode":"100828","DistrictID":1963,"WardName":"Xã Xuân Tình"},{"WardCode":"100829","DistrictID":1963,"WardName":"Xã Yên Khoái"},{"WardCode":"100803","DistrictID":1963,"WardName":"Xã Ái Quốc"},{"WardCode":"100805","DistrictID":1963,"WardName":"Xã Đồng Bục"}]}