{"data":[{"WardCode":"630509","DistrictID":2120,"WardName":"Xã Trường Xuân"},{"WardCode":"630508","DistrictID":2120,"WardName":"Xã Thuận Hạnh"},{"WardCode":"630507","DistrictID":2120,"WardName":"Xã Thuận Hà"},{"WardCode":"630506","DistrictID":2120,"WardName":"Xã Nâm N'Jang"},{"WardCode":"630505","DistrictID":2120,"WardName":"Xã Nam Bình"},{"WardCode":"630504","DistrictID":2120,"WardName":"Xã Đắk N'Dung"},{"WardCode":"630503","DistrictID":2120,"WardName":"Xã Đắk Môl"},{"WardCode":"630502","DistrictID":2120,"WardName":"Xã Đắk Hòa"},{"WardCode":"630501","DistrictID":2120,"WardName":"Thị trấn Đức An"}]}