{"data":[{"WardCode":"360501","DistrictID":2205,"WardName":"Thị trấn Sa Thầy"},{"WardCode":"360502","DistrictID":2205,"WardName":"Xã Hơ Moong"},{"WardCode":"360503","DistrictID":2205,"WardName":"Xã Mô Rai"},{"WardCode":"360504","DistrictID":2205,"WardName":"Xã Rơ Kơi"},{"WardCode":"360505","DistrictID":2205,"WardName":"Xã Sa Bình"},{"WardCode":"360506","DistrictID":2205,"WardName":"Xã Sa Nghĩa"},{"WardCode":"360507","DistrictID":2205,"WardName":"Xã Sa Nhơn"},{"WardCode":"360508","DistrictID":2205,"WardName":"Xã Sa Sơn"},{"WardCode":"360510","DistrictID":2205,"WardName":"Xã Ya Tăng"},{"WardCode":"360511","DistrictID":2205,"WardName":"Xã Ya Xiêr"},{"WardCode":"360509","DistrictID":2205,"WardName":"Xã Ya ly"}]}