{"data":[{"WardCode":"431110","DistrictID":3444,"WardName":"Xã Phước Tân"},{"WardCode":"431109","DistrictID":3444,"WardName":"Xã Phú Trung"},{"WardCode":"431108","DistrictID":3444,"WardName":"Xã Phú Riềng"},{"WardCode":"431107","DistrictID":3444,"WardName":"Xã Long Tân"},{"WardCode":"431106","DistrictID":3444,"WardName":"Xã Long Hưng"},{"WardCode":"431105","DistrictID":3444,"WardName":"Xã Long Hà"},{"WardCode":"431104","DistrictID":3444,"WardName":"Xã Long Bình"},{"WardCode":"431103","DistrictID":3444,"WardName":"Xã Bù Nho"},{"WardCode":"431102","DistrictID":3444,"WardName":"Xã Bình Tân"},{"WardCode":"431101","DistrictID":3444,"WardName":"Xã Bình Sơn"}]}